liminity/__init__.py
liminity/example.cfg
liminity/liminity.py
liminity-0.1.8.dist-info/licenses/LICENSE
liminity-0.1.8.dist-info/WHEEL
liminity-0.1.8.dist-info/entry_points.txt
liminity-0.1.8.dist-info/METADATA
liminity-0.1.8.dist-info/RECORD
