Metadata-Version: 2.4
Name: liminity
Version: 0.1.8
Summary: AI todo list demo for luciditycli's features
License-Expression: GPL-3.0-only
License-File: LICENSE
Requires-Dist: luciditycli>=0.1.4
Requires-Python: >=3.12
